pytest_pystack/__init__.py
pytest_pystack/_config.py
pytest_pystack/_debug_detect.py
pytest_pystack/_monitor_process.py
pytest_pystack/plugin.py
pytest_pystack-1.0.2.dist-info/LICENSE.txt
pytest_pystack-1.0.2.dist-info/METADATA
pytest_pystack-1.0.2.dist-info/WHEEL
pytest_pystack-1.0.2.dist-info/entry_points.txt
pytest_pystack-1.0.2.dist-info/top_level.txt
pytest_pystack-1.0.2.dist-info/RECORD
