Metadata-Version: 2.1
Name: pytest-pystack
Version: 1.0.2
Summary: Plugin to run pystack after a timeout for a test suite.
Author-email: Bloomberg LP <mcorcherojim@bloomberg.net>
License: 
Keywords: pytest,debugging,hung,pystack,bloomberg
Classifier: Intended Audience :: Developers
Classifier: Operating System :: POSIX :: Linux
Classifier: Topic :: Software Development :: Debuggers
Classifier: Programming Language :: Python :: 3.8
Classifier: Programming Language :: Python :: 3.9
Classifier: Programming Language :: Python :: 3.10
Classifier: Programming Language :: Python :: 3.11
Classifier: Programming Language :: Python :: 3.12
Classifier: Framework :: Pytest
Requires-Python: >=3.8
License-File: LICENSE.txt
Requires-Dist: pytest >=3.5.0
Requires-Dist: pystack
